jai_folder_structure/__init__.py
jai_folder_structure/py.typed
jai_folder_structure/_internal/__init__.py
jai_folder_structure/_internal/modules/__init__.py
jai_folder_structure/_internal/modules/_constants.py
jai_folder_structure/_internal/modules/_utils.py
jai_folder_structure/_internal/modules/archiver/__init__.py
jai_folder_structure/_internal/modules/archiver/_builder.py
jai_folder_structure/_internal/modules/archiver/_parsers.py
jai_folder_structure/_internal/modules/archiver/_validation.py
jai_folder_structure/_internal/modules/archiver/_zip.py
jai_folder_structure/_internal/modules/archiver/api.py
jai_folder_structure/_internal/modules/formatters/__init__.py
jai_folder_structure/_internal/modules/formatters/_csv.py
jai_folder_structure/_internal/modules/formatters/_html.py
jai_folder_structure/_internal/modules/formatters/_json.py
jai_folder_structure/_internal/modules/formatters/_list.py
jai_folder_structure/_internal/modules/formatters/_markdown.py
jai_folder_structure/_internal/modules/formatters/_tree.py
jai_folder_structure/_internal/modules/formatters/_xml.py
jai_folder_structure/_internal/modules/formatters/api.py
jai_folder_structure/_internal/modules/models/__init__.py
jai_folder_structure/_internal/modules/models/api.py
jai_folder_structure/_internal/modules/scanner/__init__.py
jai_folder_structure/_internal/modules/scanner/_filters.py
jai_folder_structure/_internal/modules/scanner/_impl.py
jai_folder_structure/_internal/modules/scanner/api.py
jai_folder_structure-1.0.0.dist-info/licenses/LICENSE
jai_folder_structure-1.0.0.dist-info/METADATA
jai_folder_structure-1.0.0.dist-info/WHEEL
jai_folder_structure-1.0.0.dist-info/top_level.txt
jai_folder_structure-1.0.0.dist-info/RECORD
