Metadata-Version: 2.4
Name: jai-folder-structure
Version: 1.0.0
Summary: Python library for analyzing and visualizing directory structures with multiple output formats, filtering, and ZIP archive creation
Author-email: JeenyJAI <JeenyJAI@gmail.com>
License: MIT
Project-URL: Homepage, https://github.com/JeenyJAI/jai-folder-structure
Project-URL: Issues, https://github.com/JeenyJAI/jai-folder-structure/issues
Classifier: License :: OSI Approved :: MIT License
Classifier: Programming Language :: Python :: 3
Classifier: Programming Language :: Python :: 3.12
Classifier: Operating System :: OS Independent
Requires-Python: >=3.12
License-File: LICENSE
Dynamic: license-file
